internxt_data_test/BigQuery.py
internxt_data_test/Schemas.py
internxt_data_test/StripeAdapter.py
internxt_data_test/__init__.py
internxt_data_test/charges_schema.py
internxt_data_test/customer_schema.py
internxt_data_test/sessions_schema.py
internxt_data_test/subscription_schema.py
internxt_data_test/utils.py
internxt_data_test-0.2.14.dist-info/WHEEL
internxt_data_test-0.2.14.dist-info/METADATA
internxt_data_test-0.2.14.dist-info/RECORD
