Metadata-Version: 2.1
Name: internxt-data-test
Version: 0.2.14
Summary: 
Author: Joan Mora
Author-email: elcorreudejoanmora@gmail.com
Requires-Python: >=3.8.0,<3.11
Classifier: Programming Language :: Python :: 3
Classifier: Programming Language :: Python :: 3.10
Classifier: Programming Language :: Python :: 3.8
Classifier: Programming Language :: Python :: 3.9
Requires-Dist: google-cloud-bigquery (>=2.34.2,<3.0.0)
Requires-Dist: pandas (>=1.4.2,<2.0.0)
Requires-Dist: pyarrow (>=7.0.0,<8.0.0)
Requires-Dist: stripe (>=2.68.0,<3.0.0)
